quillion_cli/.templates/.gitignore
quillion_cli/.templates/.q/index.html.j2
quillion_cli/.templates/app.py.j2
quillion_cli/.templates/quillion.toml.j2
quillion_cli/__init__.py
quillion_cli/cli.py
quillion_cli/commands/new.py
quillion_cli/commands/run.py
quillion_cli/config/loader.py
quillion_cli/config/models.py
quillion_cli/debug/debugger.py
quillion_cli/server/http_server.py
quillion_cli/server/websocket_server.py
quillion_cli/utils/file_downloader.py
quillion_cli/utils/file_watcher.py
quillion_cli/utils/name_formatter.py
quillion_cli/utils/templates.py
quillion_cli-0.1.5.dist-info/METADATA
quillion_cli-0.1.5.dist-info/WHEEL
quillion_cli-0.1.5.dist-info/licenses/LICENSE
quillion_cli-0.1.5.dist-info/RECORD
