Metadata-Version: 2.4
Name: quillion-cli
Version: 0.1.5
Summary: Quillion Command Line Interface
License-File: LICENSE
Author: anybody
Requires-Python: >=3.9,<4.0
Classifier: Programming Language :: Python :: 3
Classifier: Programming Language :: Python :: 3.9
Classifier: Programming Language :: Python :: 3.10
Classifier: Programming Language :: Python :: 3.11
Classifier: Programming Language :: Python :: 3.12
Classifier: Programming Language :: Python :: 3.13
Classifier: Programming Language :: Python :: 3.14
Requires-Dist: jinja2 (>=3.1.2,<4.0.0)
Requires-Dist: pyfiglet (>=1.0.4,<2.0.0)
Requires-Dist: requests (==2.32.5)
Requires-Dist: rich (>=14.1.0,<15.0.0)
Requires-Dist: tomli (>=2.0.1,<3.0.0)
Requires-Dist: typer (>=0.19.1,<0.20.0)
Requires-Dist: watchdog (>=2.3.1,<3.0.0)
